Metadata-Version: 2.4
Name: quanta-thread
Version: 1.0.1
Summary: Quantum-Inspired Computing Framework for Classical Hardware
Home-page: https://github.com/quantathread/quanta-thread
Author: QuantaThread Team
Author-email: QuantaThread Team <contact@quantathread.com>
Maintainer-email: QuantaThread Team <contact@quantathread.com>
License: MIT
Project-URL: Homepage, https://github.com/quantathread/quanta-thread
Project-URL: Documentation, https://quantathread.readthedocs.io/
Project-URL: Repository, https://github.com/quantathread/quanta-thread
Project-URL: Bug Tracker, https://github.com/quantathread/quanta-thread/issues
Project-URL: Source Code, https://github.com/quantathread/quanta-thread
Keywords: quantum computing,quantum algorithms,machine learning,artificial intelligence,optimization,parallel computing,threading
Platform: any
Classifier: Development Status :: 4 - Beta
Classifier: Intended Audience :: Developers
Classifier: Intended Audience :: Science/Research
Classifier: License :: OSI Approved :: MIT License
Classifier: Operating System :: OS Independent
Classifier: Programming Language :: Python :: 3
Classifier: Programming Language :: Python :: 3.8
Classifier: Programming Language :: Python :: 3.9
Classifier: Programming Language :: Python :: 3.10
Classifier: Programming Language :: Python :: 3.11
Classifier: Topic :: Scientific/Engineering :: Artificial Intelligence
Classifier: Topic :: Scientific/Engineering :: Physics
Classifier: Topic :: Software Development :: Libraries :: Python Modules
Requires-Python: >=3.8
License-File: LICENSE
Requires-Dist: numpy>=1.21.0
Requires-Dist: scipy>=1.7.0
Requires-Dist: matplotlib>=3.5.0
Requires-Dist: psutil>=5.8.0
Requires-Dist: requests>=2.28.0
Requires-Dist: tqdm>=4.64.0
Requires-Dist: colorama>=0.4.5
Requires-Dist: click>=8.1.0
Requires-Dist: rich>=12.0.0
Requires-Dist: networkx>=2.8.0
Requires-Dist: asyncio-mqtt>=0.11.0
Requires-Dist: pandas>=1.5.0
Provides-Extra: dev
Requires-Dist: pytest>=7.0.0; extra == "dev"
Requires-Dist: pytest-cov>=4.0.0; extra == "dev"
Requires-Dist: black>=22.0.0; extra == "dev"
Requires-Dist: flake8>=5.0.0; extra == "dev"
Requires-Dist: mypy>=0.991; extra == "dev"
Requires-Dist: pre-commit>=2.20.0; extra == "dev"
Provides-Extra: ml
Requires-Dist: tensorflow>=2.8.0; extra == "ml"
Requires-Dist: torch>=1.12.0; extra == "ml"
Requires-Dist: scikit-learn>=1.1.0; extra == "ml"
Provides-Extra: quantum
Requires-Dist: qiskit>=0.40.0; extra == "quantum"
Requires-Dist: cirq>=1.0.0; extra == "quantum"
Requires-Dist: pennylane>=0.20.0; extra == "quantum"
Provides-Extra: ai
Requires-Dist: openai>=0.27.0; extra == "ai"
Requires-Dist: google-generativeai>=0.3.0; extra == "ai"
Requires-Dist: anthropic>=0.5.0; extra == "ai"
Provides-Extra: viz
Requires-Dist: plotly>=5.10.0; extra == "viz"
Provides-Extra: jupyter
Requires-Dist: jupyter>=1.0.0; extra == "jupyter"
Requires-Dist: ipywidgets>=7.7.0; extra == "jupyter"
Provides-Extra: all
Requires-Dist: tensorflow>=2.8.0; extra == "all"
Requires-Dist: torch>=1.12.0; extra == "all"
Requires-Dist: scikit-learn>=1.1.0; extra == "all"
Requires-Dist: qiskit>=0.40.0; extra == "all"
Requires-Dist: cirq>=1.0.0; extra == "all"
Requires-Dist: pennylane>=0.20.0; extra == "all"
Requires-Dist: openai>=0.27.0; extra == "all"
Requires-Dist: google-generativeai>=0.3.0; extra == "all"
Requires-Dist: anthropic>=0.5.0; extra == "all"
Requires-Dist: plotly>=5.10.0; extra == "all"
Requires-Dist: jupyter>=1.0.0; extra == "all"
Requires-Dist: ipywidgets>=7.7.0; extra == "all"
Requires-Dist: networkx>=2.8.0; extra == "all"
Requires-Dist: asyncio-mqtt>=0.11.0; extra == "all"
Requires-Dist: pandas>=1.5.0; extra == "all"
Requires-Dist: rdkit-pypi>=2022.9.1; extra == "all"
Requires-Dist: mendeleev>=0.8.0; extra == "all"
Requires-Dist: yfinance>=0.2.0; extra == "all"
Requires-Dist: scipy>=1.7.0; extra == "all"
Requires-Dist: numba>=0.56.0; extra == "all"
Dynamic: author
Dynamic: home-page
Dynamic: license-file
Dynamic: platform
Dynamic: requires-python
